setup.py
docker_utils/__init__.py
docker_utils/entry.py
docker_utils/version.py
docker_utils.egg-info/PKG-INFO
docker_utils.egg-info/SOURCES.txt
docker_utils.egg-info/dependency_links.txt
docker_utils.egg-info/entry_points.txt
docker_utils.egg-info/requires.txt
docker_utils.egg-info/top_level.txt
docker_utils.egg-info/zip-safe
docker_utils/cmds/__init__.py
docker_utils/cmds/bash.py
docker_utils/cmds/lint.py
docker_utils/cmds/server.py
docker_utils/cmds/template.py
docker_utils/cmds/utils.py
docker_utils/tests/__init__.py
docker_utils/tests/tests.py