Metadata-Version: 1.0
Name: docker-utils
Version: 0.1.4
Summary: Utilities for Docker
Home-page: https://github.com/andymckay/docker-utils
Author: Andy McKay
Author-email: andym@mozilla.com
License: BSD
Platform: UNKNOWN
